{"note":"This file is an internal implementation detail to speed up HTML report generation. Its format can change at any time. You might be looking for the JSON report: https://coverage.rtfd.io/cmd.html#cmd-json","format":2,"version":"7.4.4","globals":"8c3333a955758b2f5be735e8971d1fd6","files":{"d_5f5a17c013354698___init___py":{"hash":"8f96e0487d400bed7b4c91e861310773","index":{"nums":[0,1,0,0,0,0,0,0],"html_filename":"d_5f5a17c013354698___init___py.html","relative_filename":"app/__init__.py"}},"d_5f5a17c013354698_mod_classes_py":{"hash":"a3258619dcf5bfe4d9d67874c8396f1b","index":{"nums":[0,1,204,0,204,0,0,0],"html_filename":"d_5f5a17c013354698_mod_classes_py.html","relative_filename":"app/mod_classes.py"}},"d_5f5a17c013354698_mod_project_py":{"hash":"0a8b970fcf05309116cea1f71c6ae42e","index":{"nums":[0,1,57,0,57,0,0,0],"html_filename":"d_5f5a17c013354698_mod_project_py.html","relative_filename":"app/mod_project.py"}}}}